<?xml version="1.0" encoding="utf-8"?>
<RoomXmlData xmlns:xsi="http://www.w3.org/2001/XMLSchema-instance" xmlns:xsd="http://www.w3.org/2001/XMLSchema">
  <type>Church</type>
  <objs>
    <ObjXmlData>
      <type>Wor_Flowers</type>
      <direction>Down</direction>
      <posX>648</posX>
      <posY>408</posY>
    </ObjXmlData>
    <ObjXmlData>
      <type>Wor_Flowers</type>
      <direction>Down</direction>
      <posX>632</posX>
      <posY>408</posY>
    </ObjXmlData>
    <ObjXmlData>
      <type>Wor_Flowers</type>
      <direction>Down</direction>
      <posX>616</posX>
      <posY>408</posY>
    </ObjXmlData>
    <ObjXmlData>
      <type>Wor_Flowers</type>
      <direction>Down</direction>
      <posX>600</posX>
      <posY>408</posY>
    </ObjXmlData>
    <ObjXmlData>
      <type>Wor_Flowers</type>
      <direction>Down</direction>
      <posX>600</posX>
      <posY>424</posY>
    </ObjXmlData>
    <ObjXmlData>
      <type>Wor_Flowers</type>
      <direction>Down</direction>
      <posX>600</posX>
      <posY>440</posY>
    </ObjXmlData>
    <ObjXmlData>
      <type>Wor_Flowers</type>
      <direction>Down</direction>
      <posX>600</posX>
      <posY>456</posY>
    </ObjXmlData>
    <ObjXmlData>
      <type>Wor_Flowers</type>
      <direction>Down</direction>
      <posX>600</posX>
      <posY>472</posY>
    </ObjXmlData>
    <ObjXmlData>
      <type>Wor_Flowers</type>
      <direction>Down</direction>
      <posX>600</posX>
      <posY>488</posY>
    </ObjXmlData>
    <ObjXmlData>
      <type>Wor_Flowers</type>
      <direction>Down</direction>
      <posX>632</posX>
      <posY>488</posY>
    </ObjXmlData>
    <ObjXmlData>
      <type>Wor_Flowers</type>
      <direction>Down</direction>
      <posX>616</posX>
      <posY>488</posY>
    </ObjXmlData>
    <ObjXmlData>
      <type>Wor_Flowers</type>
      <direction>Down</direction>
      <posX>648</posX>
      <posY>488</posY>
    </ObjXmlData>
    <ObjXmlData>
      <type>Wor_Flowers</type>
      <direction>Down</direction>
      <posX>632</posX>
      <posY>456</posY>
    </ObjXmlData>
    <ObjXmlData>
      <type>Wor_Flowers</type>
      <direction>Down</direction>
      <posX>648</posX>
      <posY>456</posY>
    </ObjXmlData>
    <ObjXmlData>
      <type>Wor_Flowers</type>
      <direction>Down</direction>
      <posX>664</posX>
      <posY>456</posY>
    </ObjXmlData>
    <ObjXmlData>
      <type>Wor_Flowers</type>
      <direction>Down</direction>
      <posX>664</posX>
      <posY>472</posY>
    </ObjXmlData>
    <ObjXmlData>
      <type>Wor_Flowers</type>
      <direction>Down</direction>
      <posX>664</posX>
      <posY>488</posY>
    </ObjXmlData>
    <ObjXmlData>
      <type>Wor_Flowers</type>
      <direction>Down</direction>
      <posX>664</posX>
      <posY>408</posY>
    </ObjXmlData>
  </objs>
</RoomXmlData>